[
  {
    "url": "https://upload.nickystore.my.id/uploads/IIVJ2g.jpg"
  },
  {
    "url": "https://upload.nickystore.my.id/uploads/yT2XYw.jpg"
  },
  {
    "url": "https://upload.nickystore.my.id/uploads/LT8TjQ.jpg"
  },
  {
    "url": "https://upload.nickystore.my.id/uploads/aIECgA.jpg"
  },
  {
    "url": "https://upload.nickystore.my.id/uploads/6VJhfw.jpg"
  },
  {
    "url": "https://upload.nickystore.my.id/uploads/PprCJA.jpg"
  },
  {
    "url": "https://upload.nickystore.my.id/uploads/yQMEjg.jpg"
  },
  {
    "url": "https://upload.nickystore.my.id/uploads/Uxxgwg.jpg"
  },
  {
    "url": "https://upload.nickystore.my.id/uploads/eKy4jw.jpg"
  },
  {
    "url": "https://upload.nickystore.my.id/uploads/0R0_vA.png"
  },
  {
    "url": "https://upload.nickystore.my.id/uploads/TGBOpQ.jpg"
  },
  {
    "url": "https://upload.nickystore.my.id/uploads/fX2sgg.jpg"
  },
  {
    "url": "https://upload.nickystore.my.id/uploads/lf0CFA.jpg"
  },
  {
    "url": "https://upload.nickystore.my.id/uploads/NQmL3A.webp"
  },
  {
    "url": "https://upload.nickystore.my.id/uploads/j2b_EQ.jpg"
  },
  {
    "url": "https://upload.nickystore.my.id/uploads/wDGdPw.jpg"
  },
  {
    "url": "https://upload.nickystore.my.id/uploads/MVIPRQ.jpg"
  },
  {
    "url": "https://upload.nickystore.my.id/uploads/4WFBjQ.jpg"
  },
  {
    "url": "https://upload.nickystore.my.id/uploads/sqCcEw.jpg"
  },
  {
    "url": "https://upload.nickystore.my.id/uploads/y00P_w.jpg"
  },
  {
    "url": "https://upload.nickystore.my.id/uploads/7jeNnQ.webp"
  },
  {
    "url": "https://upload.nickystore.my.id/uploads/JDTUOQ.jpg"
  },
  {
    "url": "https://upload.nickystore.my.id/uploads/XXzbWg.jpg"
  },
  {
    "url": "https://upload.nickystore.my.id/uploads/Uk-62A.jpg"
  },
  {
    "url": "https://upload.nickystore.my.id/uploads/5vHWag.jpg"
  },
  {
    "url": "https://upload.nickystore.my.id/uploads/vB2uQw.jpg"
  },
  {
    "url": "https://upload.nickystore.my.id/uploads/yS1eVA.webp"
  },
  {
    "url": "https://upload.nickystore.my.id/uploads/Bxl8NA.jpg"
  },
  {
    "url": "https://upload.nickystore.my.id/uploads/ls2iVQ.jpg"
  },
  {
    "url": "https://upload.nickystore.my.id/uploads/WpPnyQ.jpg"
  },
  {
    "url": "https://upload.nickystore.my.id/uploads/0nNHAw.jpg"
  },
  {
    "url": "https://upload.nickystore.my.id/uploads/vhTphg.jpg"
  },
  {
    "url": "https://upload.nickystore.my.id/uploads/v8JdLw.jpg"
  },
  {
    "url": "https://upload.nickystore.my.id/uploads/RkL9vg.png"
  },
  {
    "url": "https://upload.nickystore.my.id/uploads/1EfNCw.jpg"
  },
  {
    "url": "https://upload.nickystore.my.id/uploads/XeF6og.jpg"
  },
  {
    "url": "https://upload.nickystore.my.id/uploads/tE55dQ.jpg"
  },
  {
    "url": "https://upload.nickystore.my.id/uploads/sPlUzQ.jpg"
  },
  {
    "url": "https://upload.nickystore.my.id/uploads/nKq0hg.jpg"
  },
  {
    "url": "https://upload.nickystore.my.id/uploads/BuUDnQ.jpg"
  }
]